ktpanda/watchpylint.py
watchpylint-0.0.4.dist-info/LICENSE
watchpylint-0.0.4.dist-info/METADATA
watchpylint-0.0.4.dist-info/WHEEL
watchpylint-0.0.4.dist-info/entry_points.txt
watchpylint-0.0.4.dist-info/top_level.txt
watchpylint-0.0.4.dist-info/RECORD
