Metadata-Version: 2.1
Name: watchpylint
Version: 0.0.4
Summary: Watch for changes in Python files and run pylint on them
Home-page: https://ktpanda.org/software/watchpylint
Author: Katie Rust
Author-email: katie@ktpanda.org
License: MIT License
Classifier: Programming Language :: Python :: 3
Classifier: License :: OSI Approved :: MIT License
Classifier: Operating System :: OS Independent
Requires-Python: >=3.7
License-File: LICENSE
Requires-Dist: argcomplete>=2.0.0
